kaizen_client/__init__.py
kaizen_client/client.py
kaizen_client/decorators.py
kaizen_client/exceptions.py
kaizen_client/models.py
kaizen_client/integrations/__init__.py
kaizen_client/integrations/anthropic.py
kaizen_client/integrations/gemini.py
kaizen_client/integrations/openai.py
kaizen_client-0.1.4.dist-info/METADATA
kaizen_client-0.1.4.dist-info/WHEEL
kaizen_client-0.1.4.dist-info/top_level.txt
kaizen_client-0.1.4.dist-info/RECORD
