Metadata-Version: 2.4
Name: kaizen-client
Version: 0.1.4
Summary: Python SDK for the Kaizen Token Optimized Format (KTOF) service
Author-email: Kaizen <hello@getkaizen.com>
Project-URL: Homepage, https://github.com/getkaizen/kaizen-sdk/tree/main/python
Project-URL: Documentation, https://docs.getkaizen.io/
Project-URL: Issues, https://github.com/getkaizen/kaizen-sdk/issues
Requires-Python: >=3.10
Requires-Dist: httpx>=0.27.0
Requires-Dist: pydantic>=2.6.0
Provides-Extra: gemini
Requires-Dist: google-generativeai>=0.8.0; extra == "gemini"
Provides-Extra: openai
Requires-Dist: openai>=1.0.0; extra == "openai"
Provides-Extra: anthropic
Requires-Dist: anthropic>=0.25.0; extra == "anthropic"
Provides-Extra: all
Requires-Dist: google-generativeai>=0.8.0; extra == "all"
Requires-Dist: openai>=1.0.0; extra == "all"
Requires-Dist: anthropic>=0.25.0; extra == "all"
Requires-Dist: tiktoken>=0.5.0; extra == "all"
